cronspell/__init__.py
cronspell/_version.py
cronspell/cronspell.py
cronspell/cronspell.tx
cronspell/exceptions.py
cronspell/parse.py
cronspell/upcoming.py
cronspell/cli/__init__.py
cronspell/cli/cli.py
cronspell/cli/locate.py
cronspell/cli/parse.py
cronspell/cli/preflight.py
cronspell/cli/to_dot.py
cronspell/cli/upcoming.py
cronspell/cli/yaml.py
cronspell-0.5.0.dist-info/METADATA
cronspell-0.5.0.dist-info/WHEEL
cronspell-0.5.0.dist-info/entry_points.txt
cronspell-0.5.0.dist-info/licenses/AUTHORS.md
cronspell-0.5.0.dist-info/licenses/LICENSE.txt
cronspell-0.5.0.dist-info/RECORD
