Metadata-Version: 2.4
Name: cronspell
Version: 0.5.0
Summary: Date-expression domain specific language parsing. A neat way to express things like "First Saturday of any year", or "3rd thursdays each month" and such
Project-URL: Documentation, https://github.com/iilei/cronspell
Project-URL: Source, https://github.com/iilei/cronspell
Author-email: Jochen Preusche <922226+iilei@users.noreply.github.com>
License: MIT
License-File: AUTHORS.md
License-File: LICENSE.txt
Keywords: configuration,cron,crontab,date,datetime,dsl
Classifier: Development Status :: 4 - Beta
Classifier: Intended Audience :: Developers
Classifier: Programming Language :: Python
Classifier: Programming Language :: Python :: 3.10
Classifier: Programming Language :: Python :: 3.11
Classifier: Programming Language :: Python :: 3.12
Classifier: Programming Language :: Python :: Implementation :: CPython
Classifier: Programming Language :: Python :: Implementation :: PyPy
Classifier: Topic :: Software Development :: Libraries
Classifier: Topic :: Software Development :: User Interfaces
Requires-Python: >=3.9
Requires-Dist: textx<5,>=4.0.1
Requires-Dist: tzdata
Provides-Extra: cli
Requires-Dist: typer; extra == 'cli'
Requires-Dist: yamlpath; extra == 'cli'
